tuiview/__init__.py
tuiview/__main__.py
tuiview/__version__.py
tuiview/py.typed
tuiview/__pycache__/__init__.cpython-310.pyc
tuiview/__pycache__/__main__.cpython-310.pyc
tuiview/__pycache__/__version__.cpython-310.pyc
tuiview/cmd/alacritty.py
tuiview/cmd/cloc.py
tuiview/cmd/delta.py
tuiview/cmd/df.py
tuiview/cmd/diff.py
tuiview/cmd/du.py
tuiview/cmd/echo.py
tuiview/cmd/fd.py
tuiview/cmd/figlet.py
tuiview/cmd/git.py
tuiview/cmd/gping.py
tuiview/cmd/grep.py
tuiview/cmd/jq.py
tuiview/cmd/mods.py
tuiview/cmd/myke.py
tuiview/cmd/pandoc.py
tuiview/cmd/pastel.py
tuiview/cmd/ping.py
tuiview/cmd/rg.py
tuiview/cmd/rsync.py
tuiview/cmd/scc.py
tuiview/cmd/tree.py
tuiview/cmd/unzip.py
tuiview/cmd/watch.py
tuiview/cmd/__pycache__/alacritty.cpython-310.pyc
tuiview/cmd/__pycache__/cloc.cpython-310.pyc
tuiview/cmd/__pycache__/delta.cpython-310.pyc
tuiview/cmd/__pycache__/df.cpython-310.pyc
tuiview/cmd/__pycache__/diff.cpython-310.pyc
tuiview/cmd/__pycache__/du.cpython-310.pyc
tuiview/cmd/__pycache__/echo.cpython-310.pyc
tuiview/cmd/__pycache__/fd.cpython-310.pyc
tuiview/cmd/__pycache__/figlet.cpython-310.pyc
tuiview/cmd/__pycache__/git.cpython-310.pyc
tuiview/cmd/__pycache__/gping.cpython-310.pyc
tuiview/cmd/__pycache__/grep.cpython-310.pyc
tuiview/cmd/__pycache__/jq.cpython-310.pyc
tuiview/cmd/__pycache__/mods.cpython-310.pyc
tuiview/cmd/__pycache__/myke.cpython-310.pyc
tuiview/cmd/__pycache__/pandoc.cpython-310.pyc
tuiview/cmd/__pycache__/pastel.cpython-310.pyc
tuiview/cmd/__pycache__/ping.cpython-310.pyc
tuiview/cmd/__pycache__/rg.cpython-310.pyc
tuiview/cmd/__pycache__/rsync.cpython-310.pyc
tuiview/cmd/__pycache__/scc.cpython-310.pyc
tuiview/cmd/__pycache__/tree.cpython-310.pyc
tuiview/cmd/__pycache__/unzip.cpython-310.pyc
tuiview/cmd/__pycache__/watch.cpython-310.pyc
tuiview-0.1.1.dist-info/LICENSE
tuiview-0.1.1.dist-info/METADATA
tuiview-0.1.1.dist-info/WHEEL
tuiview-0.1.1.dist-info/entry_points.txt
tuiview-0.1.1.dist-info/top_level.txt
tuiview-0.1.1.dist-info/RECORD
